README.md
setup.py
pyprove/__init__.py
pyprove/log.py
pyprove.egg-info/PKG-INFO
pyprove.egg-info/SOURCES.txt
pyprove.egg-info/dependency_links.txt
pyprove.egg-info/not-zip-safe
pyprove.egg-info/top_level.txt
pyprove/eprover/__init__.py
pyprove/eprover/result.py
pyprove/eprover/runner.py
pyprove/expres/__init__.py
pyprove/expres/benchmarks.py
pyprove/expres/details.py
pyprove/expres/dump.py
pyprove/expres/html.py
pyprove/expres/jsdata.py
pyprove/expres/protos.py
pyprove/expres/results.py
pyprove/expres/solved.py
pyprove/expres/summary.py