Metadata-Version: 1.0
Name: pyprove
Version: 0.1
Summary: Automated Theorem Proving Tools
Home-page: http://github.com/ai4reason/pyprove
Author: ai4reason
Author-email: UNKNOWN
License: GPL3
Platform: UNKNOWN
